BMP/__init__.py
BMP/bmp.py
fractal/__init__.py
fractal/fractal.py
TestProjectAngel-1.0.0.dist-info/METADATA
TestProjectAngel-1.0.0.dist-info/WHEEL
TestProjectAngel-1.0.0.dist-info/top_level.txt
TestProjectAngel-1.0.0.dist-info/RECORD
