Metadata-Version: 2.1
Name: TestProjectAngel
Version: 1.0.0
Summary: Tools for creating a bmp file
Home-page: UNKNOWN
Author: UNKNOWN
Author-email: UNKNOWN
License: UNKNOWN
Platform: UNKNOWN
